LICENSE
MANIFEST.in
ir_fds.py
setup.cfg
setup.py
IR_FDS.egg-info/PKG-INFO
IR_FDS.egg-info/SOURCES.txt
IR_FDS.egg-info/dependency_links.txt
IR_FDS.egg-info/not-zip-safe
IR_FDS.egg-info/requires.txt
IR_FDS.egg-info/top_level.txt