Metadata-Version: 1.1
Name: IR-FDS
Version: 0.0.6
Summary: Convenient extension for Xiaomi File Storage Service
Home-page: https://coding.net/u/lvzhaoxing/p/IR-FDS
Author: Lv Zhaoxing
Author-email: lvzhaoxing@qq.com
License: MIT
Keywords: fds
Platform: any
Classifier: Development Status :: 4 - Beta
Classifier: Environment :: Web Environment
Classifier: Intended Audience :: Developers
Classifier: License :: OSI Approved :: MIT License
Classifier: Operating System :: OS Independent
Classifier: Programming Language :: Python
Classifier: Topic :: Internet :: WWW/HTTP :: Dynamic Content
Classifier: Topic :: Software Development :: Libraries :: Python Modules
